{
    "first": [
        {"name": "반가운"},
        {"name": "기쁜"},
        {"name": "울트라"},
        {"name": "즐거운"},
        {"name": "행복한"},
        {"name": "놀란"},
        {"name": "당황한"},
        {"name": "신나는"},
        {"name": "서늘한"},
        {"name": "따뜻한"}
    ],
    "last": [
        {"name": "참새"},
        {"name": "바람"},
        {"name": "구름"},
        {"name": "하늘"},
        {"name": "별"},
        {"name": "달"},
        {"name": "태양"},
        {"name": "강"},
        {"name": "산"},
        {"name": "들"}
    ]
}